pytest_idapro
