Metadata-Version: 1.2
Name: pytest-idapro
Version: 0.4.2
Summary: A pytest plugin for idapython. Allows a pytest setup to run tests outside and inside IDA in an automated manner by runnig pytest inside IDA and by mocking idapython api
Home-page: https://github.com/nirizr/pytest-idapro
Author: Nir Izraeli
Author-email: nirizr@gmail.com
Maintainer: Nir Izraeli
Maintainer-email: nirizr@gmail.com
License: UNKNOWN
Keywords: testing,pytest,idapython,idapro
Platform: UNKNOWN
Classifier: Intended Audience :: Developers
Classifier: Topic :: Software Development :: Testing
Classifier: Operating System :: OS Independent
Classifier: Programming Language :: Python
Classifier: Programming Language :: Python :: 2.7
Classifier: Programming Language :: Python :: 3.4
